[
  {
    "title": "Why This Kolaveri Di",
    "artist": "Dhanush",
    "tags": "funny playful quirky emotional heartbreak tamil viral soft beat"
  },
  {
    "title": "Rowdy Baby",
    "artist": "Dhanush, Dhee",
    "tags": "upbeat dance energetic tamil feel good party"
  },
  {
    "title": "Vaathi Coming",
    "artist": "Anirudh Ravichander",
    "tags": "high energy dance tamil mass hype motivational"
  },
  {
    "title": "Arabic Kuthu",
    "artist": "Anirudh Ravichander, Jonita Gandhi",
    "tags": "dance upbeat party tamil kuthu fun rhythm"
  },
  {
    "title": "Kanave Kanave",
    "artist": "Anirudh Ravichander",
    "tags": "sad emotional deep heartbreak tamil soulful"
  },
  {
    "title": "Naan Pizhaippeno",
    "artist": "A.R. Rahman",
    "tags": "romantic emotional soothing tamil love calm lyrical"
  },
  {
    "title": "Tum Tum",
    "artist": "Sri Vardhini, Satya Yamini",
    "tags": "romantic cute feel good tamil wedding trending"
  },
  {
    "title": "Shape of You",
    "artist": "Ed Sheeran",
    "tags": "dance pop upbeat energetic romantic fun"
  },
  {
    "title": "Blinding Lights",
    "artist": "The Weeknd",
    "tags": "synth pop retro energetic upbeat driving night"
  },
  {
    "title": "Someone Like You",
    "artist": "Adele",
    "tags": "sad emotional heartbreak mellow slow piano soulful"
  },
  {
    "title": "Believer",
    "artist": "Imagine Dragons",
    "tags": "powerful energetic motivational rock workout intensity"
  },
  {
    "title": "Levitating",
    "artist": "Dua Lipa",
    "tags": "happy pop dance upbeat fun bright"
  },
  {
    "title": "Perfect",
    "artist": "Ed Sheeran",
    "tags": "romantic soft emotional love wedding slow calm"
  },
  {
    "title": "Fix You",
    "artist": "Coldplay",
    "tags": "emotional healing soft inspirational slow uplifting"
  },

  {
    "title": "Ocean Breathes",
    "artist": "CalmSphere",
    "tags": "calm soothing ambient relaxation water waves peace"
  },
  {
    "title": "Rush Hour Run",
    "artist": "BeatDrive",
    "tags": "energetic workout motivation fast tempo adrenaline"
  },
  {
    "title": "Night Thoughts",
    "artist": "DeepSoul",
    "tags": "sad emotional mellow slow piano reflective"
  },
  {
    "title": "Morning Boost",
    "artist": "SunBurst",
    "tags": "happy upbeat cheerful vibrant uplifting positivity"
  },
  {
    "title": "Cloud Drifter",
    "artist": "SkyFlow",
    "tags": "lofi chill beats focus study relaxing smooth"
  },
  {
    "title": "Thunder Sprint",
    "artist": "VoltX",
    "tags": "aggressive energetic intense fast electric hype"
  },
  {
    "title": "Silk Dreams",
    "artist": "MoonWave",
    "tags": "soft calm dreamy ethereal soothing sleep"
  },
  {
    "title": "Fire Within",
    "artist": "CoreBeat",
    "tags": "motivational powerful energetic gym strength"
  },
  {
    "title": "Blue Horizon",
    "artist": "TranquilSky",
    "tags": "calm peaceful open airy meditation"
  },
  {
    "title": "JoyRide",
    "artist": "ColorTone",
    "tags": "happy dance upbeat fun bright party vibes"
  }
]
